{
  "cosmic-salad-130": {
    "run_name": "cosmic-salad-130",
    "embedding_size": 256,
    "hidden_size": 64,
    "intermediate_size": 1024,
    "num_attention_heads": 8,
    "num_hidden_layers": 8
  },
  "giddy-planet-101": {
    "run_name": "giddy-planet-101",
    "embedding_size": 256,
    "hidden_size": 256,
    "intermediate_size": 1024,
    "num_attention_heads": 1,
    "num_hidden_layers": 8
  },
  "dutiful-meadow-131": {
    "run_name": "dutiful-meadow-131",
    "embedding_size": 256,
    "hidden_size": 32,
    "intermediate_size": 1024,
    "num_attention_heads": 8,
    "num_hidden_layers": 8
  },
  "rural-serenity-126": {
    "run_name": "rural-serenity-126",
    "embedding_size": 256,
    "hidden_size": 128,
    "intermediate_size": 1024,
    "num_attention_heads": 8,
    "num_hidden_layers": 8
  },
  "skilled-grass-125": {
    "run_name": "skilled-grass-125",
    "embedding_size": 256,
    "hidden_size": 256,
    "intermediate_size": 1024,
    "num_attention_heads": 8,
    "num_hidden_layers": 8
  },
  "tough-wave-128": {
    "run_name": "tough-wave-128",
    "embedding_size": 256,
    "hidden_size": 256,
    "intermediate_size": 1024,
    "num_attention_heads": 2,
    "num_hidden_layers": 8
  },
  "vivid-dust-127": {
    "run_name": "vivid-dust-127",
    "embedding_size": 256,
    "hidden_size": 256,
    "intermediate_size": 1024,
    "num_attention_heads": 4,
    "num_hidden_layers": 8
  }
}